cortexgraph/__init__.py
cortexgraph/background.py
cortexgraph/config.py
cortexgraph/context.py
cortexgraph/performance.py
cortexgraph/server.py
cortexgraph/activation/__init__.py
cortexgraph/activation/activation.yaml.example
cortexgraph/activation/config.py
cortexgraph/activation/detectors.py
cortexgraph/activation/entity_extraction.py
cortexgraph/activation/models.py
cortexgraph/activation/patterns.py
cortexgraph/agents/__init__.py
cortexgraph/agents/base.py
cortexgraph/agents/beads_integration.py
cortexgraph/agents/cluster_detector.py
cortexgraph/agents/decay_analyzer.py
cortexgraph/agents/ltm_promoter.py
cortexgraph/agents/models.py
cortexgraph/agents/rate_limiter.py
cortexgraph/agents/relationship_discovery.py
cortexgraph/agents/scheduler.py
cortexgraph/agents/semantic_merge.py
cortexgraph/agents/storage_utils.py
cortexgraph/backup/__init__.py
cortexgraph/backup/git_backup.py
cortexgraph/cli/__init__.py
cortexgraph/cli/consolidate.py
cortexgraph/cli/migrate.py
cortexgraph/core/__init__.py
cortexgraph/core/auto_recall.py
cortexgraph/core/clustering.py
cortexgraph/core/consolidation.py
cortexgraph/core/decay.py
cortexgraph/core/math_utils.py
cortexgraph/core/pagination.py
cortexgraph/core/review.py
cortexgraph/core/scoring.py
cortexgraph/core/search_common.py
cortexgraph/core/similarity.py
cortexgraph/core/text_utils.py
cortexgraph/integration/__init__.py
cortexgraph/integration/cortex_memory.py
cortexgraph/preprocessing/__init__.py
cortexgraph/preprocessing/entity_extractor.py
cortexgraph/preprocessing/importance_scorer.py
cortexgraph/preprocessing/phrase_detector.py
cortexgraph/security/__init__.py
cortexgraph/security/logging.py
cortexgraph/security/paths.py
cortexgraph/security/permissions.py
cortexgraph/security/secrets.py
cortexgraph/security/validators.py
cortexgraph/storage/__init__.py
cortexgraph/storage/jsonl_storage.py
cortexgraph/storage/ltm_index.py
cortexgraph/storage/maintenance.py
cortexgraph/storage/models.py
cortexgraph-1.2.1.dist-info/METADATA
cortexgraph-1.2.1.dist-info/WHEEL
cortexgraph-1.2.1.dist-info/entry_points.txt
cortexgraph-1.2.1.dist-info/licenses/LICENSE
cortexgraph-1.2.1.dist-info/RECORD
